{
  "tweets": [
    {
      "mentions": [],
      "retweeters": [
        "@k56568464", "@Iace_io", "@CryptoExplore0x", "@0x_visionary", "@AIRDROPSOLIAIR", "@EUrstrand",
        "@SusanPe43070254", "@Trigeminalfnhu1", "@Michael98773", "@kave04851060", "@DonBOS744", "@sofiahorton_04",
        "@MoneyJrodPRIV", "@KhanuengK", "@intertreeJK", "@elmerjm9", "@IOHK_Charless_1", "@maxkuz81", "@surbahanxbt_",
        "@elonmusktrump24", "@ali_rahyab", "@kyoshiro7904", "@Olusch85", "@DinarAsenjo", "@vivi1_adapool",
        "@muftiadja2024", "@IOHK_Charlless", "@Hahero7", "@Danni33302647", "@vhvc246843", "@NamiiToken", "@MedVassili",
        "@alotofck1", "@Chris_Dev0", "@nitabaladewa", "@DevdasLark31873", "@Xavier44465Vrz", "@ParaisoLamas",
        "@Autumn54886584", "@nJaRzLVyqaWRt1K", "@ChrisSaSoriya", "@BeepBoopBeep666", "@STORM_Partners", "@MaxEugster2",
        "@DiamondAnother", "@ysf63943452", "@Krittidech5", "@Cryptonitehands", "@mattpiz", "@Gotterdammeru12",
        "@k45tor", "@pinguim_mateus", "@sasse575", "@Saeed58786680", "@SteveCapric", "@KagameLee", "@ctrl_alt_joe",
        "@EdnStuff", "@jaybrrr2", "@BC3isWeb3", "@jm_chiclana", "@NummusPopuli", "@5050isawin", "@Johnny219098579",
        "@Chris77God", "@FedericoGaretti", "@suresh071292", "@MiguelRobinson_", "@Forward241321", "@ravenpoolnet",
        "@cryptog91326431", "@erocks79", "@everfer93", "@blockchainned", "@IOHK_Charles", "@voye27890517",
        "@olafrendos", "@Cryptoboo27", "@ADA_bull_2025", "@CryptickN49", "@RealJohnSanti", "@kiwipooI", "@adaholderr",
        "@LawrenceEn57481", "@adnanansari_07", "@Sourabh00190", "@DattatrayaKash2", "@Sher_Ahmad1", "@IvanSpirit2017",
        "@Aldure85", "@JonKanh", "@IsauroBargas", "@IronMaidenJ", "@CryptoPedroR", "@L0veWarr1or", "@Cydenime"
      ],
      "tweetID": "1861047203890085911"
    }, {
      "mentions": [],
      "retweeters": [
        "@yoirowallet", "@Iace_io", "@Trigeminalfnhu1", "@keichero187", "@RiedersbergerM", "@PChiziane",
        "@EseWilliams5", "@romg9385", "@Sher_Ahmad1", "@Little_GrayMan", "@willy_morriss", "@Ivan1950720", "@Rk_Jai009",
        "@RenatoMaxx23"
      ],
      "tweetID": "1862845200097214501"
    }, {
      "mentions": [],
      "retweeters": ["@Cabdiqani2021", "@Ivan1950720", "@yojoflo", "@Richie20766061", "@RenatoMaxx23"],
      "tweetID": "1862845207277924581"
    }, {
      "mentions": [
        "@adamKDean", "@BeatriceAnihiri", "@Cerkoryn", "@F_Gregaard", "@giozzi", "@hansen_eystein", "@indi_gital",
        "@intertreeJK", "@JBriggsLondon", "@NicolasC3rny", "@nicola_massella", "@yuta_cryptox"
      ],
      "retweeters": [
        "@Rk_Jai009", "@SDMfe2", "@ShamanAustrali", "@DefiDavis20", "@MBellVerse", "@Johnnie97071737",
        "@Arifin55607566", "@AppelgrenJesper", "@vhvc246843", "@Levi7593655", "@Klovakstyle", "@Shahrokh1743849",
        "@PChiziane", "@Arquitecto2030", "@Gen_R_8", "@Cerkoryn", "@clarkalesna", "@intertreeJK", "@DenicioBernier",
        "@BeatriceAnihiri"
      ],
      "tweetID": "1862552024467804534"
    }, {
      "mentions": [],
      "retweeters": ["@faizalmadaniku", "@SDMfe2", "@DenicioBernier"],
      "tweetID": "1862552028246896665"
    }, {
      "mentions": ["@JeremyFirsterCF"],
      "retweeters": [
        "@FranciscoH59407", "@AppelgrenJesper", "@Ciprian30460409", "@Sher_Ahmad1", "@PChiziane", "@DefiDavis20",
        "@MBellVerse", "@geulinchalseu1", "@k56568464", "@JoriPLevy", "@ba34by0q"
      ],
      "tweetID": "1862213021369590001"
    }, {
      "mentions": ["@NicolasC3rny", "@Cardano_CF"],
      "retweeters": [
        "@peperayo29", "@SuccessenaiH", "@pavank1lla", "@FelixZk033", "@daniel_ATL_84", "@Jennycitalinda",
        "@vhvc246843", "@Shahrokh1743849", "@MJakoao", "@Hahero7", "@RiedersbergerM", "@ayudame_freud", "@PChiziane",
        "@yojoflo", "@AudacTruth", "@superbatvcf", "@0xWhaleKing", "@RadekHampl10", "@NdokwaI", "@frank_alowishus",
        "@Duncan_TheFox", "@T_Avianto", "@JeremyPrieto64", "@werderforever18", "@CardanoSaint", "@thotman__",
        "@planetmaaz", "@pookimikos", "@OrhanMUTLU1903", "@therealShaffy"
      ],
      "tweetID": "1855665901774782650"
    }, {
      "mentions": ["@NucastIO", "@Charanz1309"],
      "retweeters": [
        "@peperayo29", "@gaja2408", "@vhvc246843", "@RiedersbergerM", "@0xWhaleKing", "@hemidalcardano",
        "@TechnicalHashg1", "@LionKhan111", "@pavank1lla", "@ChezPierree", "@TheLarsOfUs", "@Moittio", "@daniel_ATL_84",
        "@travlookingayal", "@RefreshedPixel", "@Charanz1309", "@VinaWizard", "@JooAlex56689913", "@CardanoSaint",
        "@juancp1861", "@Lasertberl", "@AlecsanderMihai", "@Arquitecto2030", "@Levi7593655", "@ChrisSaSoriya",
        "@Yo74247179Yo", "@PChiziane", "@blueprintofbook", "@mmustaphayakubu", "@fayaz0_", "@DenicioBernier"
      ],
      "tweetID": "1855257932079813057"
    }, {
      "mentions": [],
      "retweeters": [
        "@peperayo29", "@RiedersbergerM", "@0xWhaleKing", "@hemidalcardano", "@ChezPierree", "@pavank1lla",
        "@LuisQui83512018", "@Moittio", "@fernnwehh_", "@Arquitecto2030", "@nJaRzLVyqaWRt1K", "@Zoo_b_zoo_",
        "@snickertony", "@JooAlex56689913", "@Nichola43910835", "@Charizzard112", "@CardanoMasr", "@ChrisSaSoriya",
        "@VISHWAMEET95570", "@VinaWizard", "@papo24101991", "@0rkl4", "@Arifin55607566", "@xxavxander5323",
        "@iwolf_crypto", "@Levi7593655", "@PChiziane", "@Blockbit_office", "@DanielP1527", "@Dvdking78",
        "@ThomasR37293208", "@AlecsanderMihai", "@lisakfigo", "@RealJohnSanti", "@WorldOfGaia5Art", "@planetmaaz"
      ],
      "tweetID": "1855202299682984314"
    }, {
      "mentions": ["@matiwinnetou", "@satran004"],
      "retweeters": [
        "@LoriNelson16763", "@peperayo29", "@hemidalcardano", "@Moittio", "@don_beyer5", "@Iearncardano", "@Hahero7",
        "@pty_1982", "@RiedersbergerM", "@PChiziane", "@AnastasiaLabs", "@PEACETALKSNOW", "@mattpiz", "@matiwinnetou",
        "@Xyq384", "@cardanesia", "@Klovakstyle", "@techdad777", "@JemyIragi", "@AkhedTaiekh", "@MauroAndreoliA"
      ],
      "tweetID": "1854534438006247848"
    }
  ],
  "username": "@Cardano"
}